mcs_plugin_manager/__init__.py
mcs_plugin_manager-0.0.0.dist-info/METADATA
mcs_plugin_manager-0.0.0.dist-info/WHEEL
mcs_plugin_manager-0.0.0.dist-info/RECORD
