Metadata-Version: 2.4
Name: mcs-plugin-manager
Version: 0.0.0
Project-URL: Repository, https://gitlab.com/tictaccc/mcs-plugin-manager
